nmurl/__init__.py
nmurl/main.py
nmurl/parsedns.py
nmurl/parsenmap.py
nmurl-1.3.3.dist-info/LICENSE
nmurl-1.3.3.dist-info/METADATA
nmurl-1.3.3.dist-info/WHEEL
nmurl-1.3.3.dist-info/entry_points.txt
nmurl-1.3.3.dist-info/top_level.txt
nmurl-1.3.3.dist-info/RECORD
